pick3letters/__init__.py
pick3letters/generate.py
pick3letters/magnet.py
pick3letters/pick3letters.py
pick3letters/prefixes.py
pick3letters-1.0.0.dist-info/COPYING
pick3letters-1.0.0.dist-info/METADATA
pick3letters-1.0.0.dist-info/WHEEL
pick3letters-1.0.0.dist-info/entry_points.txt
pick3letters-1.0.0.dist-info/top_level.txt
pick3letters-1.0.0.dist-info/RECORD
