Metadata-Version: 2.1
Name: pick3letters
Version: 1.0.0
Summary: Convert hex strings and magnet links to poetry or prose.
Home-page: https://github.com/seanlynch/pick3letters
Author: Sean R. Lynch
Author-email: seanl@literati.org
License: UNKNOWN
Keywords: bittorrent
Platform: UNKNOWN
Classifier: Development Status :: 3 - Alpha
Classifier: License :: OSI Approved :: GNU Affero General Public License v3 or later (AGPLv3+)
Classifier: Programming Language :: Python :: 3
Classifier: Programming Language :: Python :: 3.6
Classifier: Programming Language :: Python :: 3.7
Classifier: Programming Language :: Python :: 3.8
Classifier: Programming Language :: Python :: 3.9
Classifier: Programming Language :: Python :: 3 :: Only
Requires-Python: >=3.6, <4
License-File: COPYING
